pytest_mock_server.py
pytest_mock_server-0.3.0.dist-info/LICENSE
pytest_mock_server-0.3.0.dist-info/METADATA
pytest_mock_server-0.3.0.dist-info/WHEEL
pytest_mock_server-0.3.0.dist-info/entry_points.txt
pytest_mock_server-0.3.0.dist-info/top_level.txt
pytest_mock_server-0.3.0.dist-info/RECORD
