Metadata-Version: 2.1
Name: pytest-mock-server
Version: 0.3.0
Summary: Mock server plugin for pytest
Home-page: https://github.com/AndreyErmilov/pytest-mock-server
Author: Andrey Ermilov
Author-email: andrerm@ya.ru
Maintainer: Andrey Ermilov
Maintainer-email: andrerm@ya.ru
License: MIT
Platform: UNKNOWN
Classifier: Development Status :: 4 - Beta
Classifier: Framework :: Pytest
Classifier: Intended Audience :: Developers
Classifier: Topic :: Software Development :: Testing
Classifier: Programming Language :: Python
Classifier: Programming Language :: Python :: 3
Classifier: Programming Language :: Python :: 3.4
Classifier: Programming Language :: Python :: 3.5
Classifier: Programming Language :: Python :: 3.6
Classifier: Programming Language :: Python :: 3.7
Classifier: Programming Language :: Python :: Implementation :: CPython
Classifier: Programming Language :: Python :: Implementation :: PyPy
Classifier: Operating System :: OS Independent
Classifier: License :: OSI Approved :: MIT License
Requires-Python: >=3.0
License-File: LICENSE
Requires-Dist: pytest (>=3.5.0)
Requires-Dist: flask (>=1.0)
